mozilla_linux_pkg_manager/__init__.py
mozilla_linux_pkg_manager/cli.py
mozilla_linux_pkg_manager-0.1.0.dist-info/LICENSE
mozilla_linux_pkg_manager-0.1.0.dist-info/METADATA
mozilla_linux_pkg_manager-0.1.0.dist-info/WHEEL
mozilla_linux_pkg_manager-0.1.0.dist-info/entry_points.txt
mozilla_linux_pkg_manager-0.1.0.dist-info/RECORD
