Metadata-Version: 2.1
Name: mozilla-linux-pkg-manager
Version: 0.1.0
Summary: `mozilla-releng/mozilla-linux-pkg-manager` is a Python tool for managing Mozilla `.deb` packages.
License: MPL-2.0
Author: Mozilla Release Engineering
Author-email: release@mozilla.com
Requires-Python: >=3.11,<4.0
Classifier: License :: OSI Approved
Classifier: Programming Language :: Python :: 3
Classifier: Programming Language :: Python :: 3.11
Requires-Dist: aiohttp (>=3.8.6,<4.0.0)
Requires-Dist: google-cloud-artifact-registry (>=1.9.0,<2.0.0)
Requires-Dist: mozilla-version (>=2.1.0,<3.0.0)
Requires-Dist: pyyaml (>=6.0.1,<7.0.0)
